liveedit/__init__.py
liveedit/forms.py
liveedit/models.py
liveedit/urls.py
liveedit/utils.py
liveedit/views.py
liveedit/static/css/liveedit.css
liveedit/static/js/liveedit.js
liveedit/templates/liveedit/edit_panel.html
liveedit/templatetags/__init__.py
liveedit/templatetags/liveedit.py
wagtail_liveedit-0.0.23.dist-info/LICENSE
wagtail_liveedit-0.0.23.dist-info/METADATA
wagtail_liveedit-0.0.23.dist-info/WHEEL
wagtail_liveedit-0.0.23.dist-info/top_level.txt
wagtail_liveedit-0.0.23.dist-info/RECORD
