Metadata-Version: 2.2
Name: wagtail-liveedit
Version: 0.0.23
Summary: Live editing add-on for Wagtail CMS
Home-page: https://github.com/jonny5532/wagtail-liveedit
Author: jonny5532
License: MIT
Classifier: Programming Language :: Python :: 3
Classifier: License :: OSI Approved :: MIT License
Classifier: Operating System :: OS Independent
Classifier: Framework :: Wagtail
License-File: LICENSE
Requires-Dist: wagtail<7.3,>=5.2.8
Dynamic: author
Dynamic: classifier
Dynamic: home-page
Dynamic: license
Dynamic: requires-dist
Dynamic: summary
